universalmutator/__init__.py
universalmutator/analyze.py
universalmutator/c_handler.py
universalmutator/checkcov.py
universalmutator/cpp_handler.py
universalmutator/fe_handler.py
universalmutator/findmissing.py
universalmutator/fortran_handler.py
universalmutator/genmutants.py
universalmutator/go_handler.py
universalmutator/intersect.py
universalmutator/java_handler.py
universalmutator/javascript_handler.py
universalmutator/lisp_handler.py
universalmutator/mutator.py
universalmutator/prioritize.py
universalmutator/prune.py
universalmutator/python_handler.py
universalmutator/r_handler.py
universalmutator/rust_handler.py
universalmutator/server.py
universalmutator/show.py
universalmutator/solidity_handler.py
universalmutator/swift_handler.py
universalmutator/utils.py
universalmutator/vyper_handler.py
universalmutator/comby/c.rules
universalmutator/comby/c_like.rules
universalmutator/comby/cpp.rules
universalmutator/comby/fortran.rules
universalmutator/comby/go.rules
universalmutator/comby/java.rules
universalmutator/comby/lisp.rules
universalmutator/comby/none.rules
universalmutator/comby/python.rules
universalmutator/comby/r.rules
universalmutator/comby/rust.rules
universalmutator/comby/solidity.rules
universalmutator/comby/swift.rules
universalmutator/comby/universal.rules
universalmutator/comby/vyper.rules
universalmutator/static/c.rules
universalmutator/static/c_like.rules
universalmutator/static/cpp.rules
universalmutator/static/fe.rules
universalmutator/static/fortran.rules
universalmutator/static/go.rules
universalmutator/static/java.rules
universalmutator/static/javascript.rules
universalmutator/static/lisp.rules
universalmutator/static/none.rules
universalmutator/static/python.rules
universalmutator/static/r.rules
universalmutator/static/rust.rules
universalmutator/static/solidity.rules
universalmutator/static/swift.rules
universalmutator/static/universal.rules
universalmutator/static/vyper.rules
universalmutator-1.1.11.dist-info/LICENSE
universalmutator-1.1.11.dist-info/METADATA
universalmutator-1.1.11.dist-info/WHEEL
universalmutator-1.1.11.dist-info/entry_points.txt
universalmutator-1.1.11.dist-info/top_level.txt
universalmutator-1.1.11.dist-info/RECORD
