Metadata-Version: 2.1
Name: universalmutator
Version: 1.1.11
Summary: Universal regexp-based mutation tool
Home-page: https://github.com/agroce/universalmutator
License: MIT
Keywords: testing mutation mutation-testing
Platform: UNKNOWN
Classifier: Intended Audience :: Developers
Classifier: Development Status :: 4 - Beta
Classifier: Programming Language :: Python :: 2
Classifier: Programming Language :: Python :: 3
Requires-Dist: comby
Requires-Dist: python-levenshtein
Requires-Dist: tabulate
